LICENSE.txt
MANIFEST.in
README.rst
setup.py
cryptop/__init__.py
cryptop/config.ini
cryptop/cryptop.py
cryptop.egg-info/PKG-INFO
cryptop.egg-info/SOURCES.txt
cryptop.egg-info/dependency_links.txt
cryptop.egg-info/entry_points.txt
cryptop.egg-info/requires.txt
cryptop.egg-info/top_level.txt