Metadata-Version: 1.1
Name: cryptop
Version: 0.2.0
Summary: Command line Cryptocurrency Portfolio
Home-page: https://github.com/huwwp/cryptop
Author: huwwp
Author-email: hpigott@gmail.com
License: MIT
Keywords: crypto cli portfolio curses cryptocurrency bitcoin
Platform: UNKNOWN
Classifier: Programming Language :: Python
Classifier: Programming Language :: Python :: 3
